knetvis/__init__.py
knetvis/cli.py
knetvis/models.py
knetvis/policy.py
knetvis/simulator.py
knetvis/visualizer.py
knetvis-0.1.1.dist-info/LICENSE
knetvis-0.1.1.dist-info/METADATA
knetvis-0.1.1.dist-info/WHEEL
knetvis-0.1.1.dist-info/entry_points.txt
knetvis-0.1.1.dist-info/top_level.txt
knetvis-0.1.1.dist-info/RECORD
