Metadata-Version: 2.2
Name: knetvis
Version: 0.1.1
Summary: A CLI tool for Kubernetes Network Policy visualization
Home-page: https://github.com/yourusername/knetvis
Author: Samuel Arogbonlo
Author-email: Samuel Arogbonlo <sbayo971@gmail.com>
Classifier: Development Status :: 3 - Alpha
Classifier: Intended Audience :: Developers
Classifier: License :: OSI Approved :: MIT License
Classifier: Operating System :: OS Independent
Classifier: Programming Language :: Python :: 3
Classifier: Programming Language :: Python :: 3.8
Classifier: Programming Language :: Python :: 3.9
Classifier: Programming Language :: Python :: 3.10
Classifier: Topic :: Software Development :: Libraries :: Python Modules
Requires-Python: >=3.8
License-File: LICENSE
Requires-Dist: kubernetes>=28.1.0
Requires-Dist: networkx>=3.1
Requires-Dist: matplotlib>=3.7.1
Requires-Dist: click>=8.1.3
Requires-Dist: rich>=13.3.5
Requires-Dist: pyyaml>=6.0.1
Dynamic: author
Dynamic: home-page
Dynamic: requires-python
